deeplabcut2yolo/__about__.py
deeplabcut2yolo/__init__.py
deeplabcut2yolo/deeplabcut2yolo.py
deeplabcut2yolo-2.2.9.dist-info/licenses/LICENSE
deeplabcut2yolo-2.2.9.dist-info/METADATA
deeplabcut2yolo-2.2.9.dist-info/WHEEL
deeplabcut2yolo-2.2.9.dist-info/top_level.txt
deeplabcut2yolo-2.2.9.dist-info/RECORD
