Metadata-Version: 2.4
Name: deeplabcut2yolo
Version: 2.2.9
Summary: Convert DeepLabCut dataset to YOLO format
Author-email: Sira Pornsiriprasert <code@psira.me>
Maintainer-email: Sira Pornsiriprasert <code@psira.me>
Project-URL: Homepage, https://github.com/p-sira/deeplabcut2yolo
Project-URL: Repository, https://github.com/p-sira/deeplabcut2yolo
Project-URL: Issues, https://github.com/p-sira/deeplabcut2yolo/issues
Project-URL: Documentation, https://p-sira.github.io/deeplabcut2yolo/
Classifier: Programming Language :: Python :: 3
Classifier: Programming Language :: Python :: 3.10
Classifier: Programming Language :: Python :: 3.11
Classifier: Programming Language :: Python :: 3.12
Classifier: Programming Language :: Python :: 3.13
Classifier: Operating System :: OS Independent
Classifier: Topic :: Scientific/Engineering :: Artificial Intelligence
Classifier: License :: OSI Approved :: GNU General Public License v3 (GPLv3)
Classifier: License :: OSI Approved :: BSD License
Requires-Python: >=3.10
License-File: LICENSE
Requires-Dist: numpy
Requires-Dist: pyyaml
Requires-Dist: ruamel-yaml
Dynamic: license-file
